<?xml version="1.0" encoding="UTF-8"?>

<Processor Type="SynthChain" ID="Rausch" Bypassed="0" Gain="0.6025595664978027"
           Balance="0.0" VoiceLimit="64.0" KillFadeTime="20.0" IconColour="0"
           packageName="" BuildVersion="650">
  <ChildProcessors>
    <Processor Type="MidiProcessorChain" ID="Midi Processor" Bypassed="0">
      <ChildProcessors>
        <Processor Type="ScriptProcessor" ID="Interface" Bypassed="0">
          <ChildProcessors/>
          <Content>
            <Control type="ScriptSlider" id="Rate_defaultKnb" value="0.0"/>
            <Control type="ScriptSlider" id="Mix_defaultKnb" value="0.4000000059604645"/>
            <Control type="ScriptSlider" id="Rez_defaultKnb" value="0.5"/>
            <Control type="ScriptButton" id="Next_iconBtn" value="0.0"/>
            <Control type="ScriptButton" id="Prev_iconBtn" value="0.0"/>
            <Control type="ScriptButton" id="Button1" value="0.0"/>
            <Control type="ScriptSlider" id="Volyme_RingKnb" value="0.0"/>
          </Content>
          <UIData Source="RauschUIData"/>
        </Processor>
      </ChildProcessors>
    </Processor>
    <Processor Type="ModulatorChain" ID="GainModulation" Bypassed="0" Intensity="1.0">
      <ChildProcessors/>
    </Processor>
    <Processor Type="ModulatorChain" ID="PitchModulation" Bypassed="1" Intensity="0.0">
      <ChildProcessors/>
    </Processor>
    <Processor Type="EffectChain" ID="FX" Bypassed="0">
      <ChildProcessors>
        <Processor Type="HardcodedMasterFX" ID="Filter" Bypassed="0" Network="Filter"
                   Filter="0.5" Tempo="4.0" Mix="50.0" Smooth="34.60000228881836">
          <ChildProcessors>
            <Processor Type="ModulatorChain" ID="P1 Modulation" Bypassed="1" Intensity="1.0">
              <ChildProcessors/>
            </Processor>
            <Processor Type="ModulatorChain" ID="P2 Modulation" Bypassed="1" Intensity="1.0">
              <ChildProcessors/>
            </Processor>
            <Processor Type="ModulatorChain" ID="P3 Modulation" Bypassed="1" Intensity="1.0">
              <ChildProcessors/>
            </Processor>
            <Processor Type="ModulatorChain" ID="P4 Modulation" Bypassed="1" Intensity="1.0">
              <ChildProcessors/>
            </Processor>
            <Processor Type="ModulatorChain" ID="P5 Modulation" Bypassed="1" Intensity="1.0">
              <ChildProcessors/>
            </Processor>
            <Processor Type="ModulatorChain" ID="P6 Modulation" Bypassed="1" Intensity="1.0">
              <ChildProcessors/>
            </Processor>
            <Processor Type="ModulatorChain" ID="P7 Modulation" Bypassed="1" Intensity="1.0">
              <ChildProcessors/>
            </Processor>
            <Processor Type="ModulatorChain" ID="P8 Modulation" Bypassed="1" Intensity="1.0">
              <ChildProcessors/>
            </Processor>
          </ChildProcessors>
          <RoutingMatrix NumSourceChannels="2" Channel0="0" Send0="-1" Channel1="1" Send1="-1"/>
        </Processor>
        <Processor Type="HardcodedMasterFX" ID="DeRez" Bypassed="0" Network="Crush"
                   Mix="0.4000000059604645" Rate="0.0" Rez="0.5">
          <ChildProcessors>
            <Processor Type="ModulatorChain" ID="P1 Modulation" Bypassed="1" Intensity="1.0">
              <ChildProcessors/>
            </Processor>
            <Processor Type="ModulatorChain" ID="P2 Modulation" Bypassed="1" Intensity="1.0">
              <ChildProcessors/>
            </Processor>
            <Processor Type="ModulatorChain" ID="P3 Modulation" Bypassed="1" Intensity="1.0">
              <ChildProcessors/>
            </Processor>
            <Processor Type="ModulatorChain" ID="P4 Modulation" Bypassed="1" Intensity="1.0">
              <ChildProcessors/>
            </Processor>
            <Processor Type="ModulatorChain" ID="P5 Modulation" Bypassed="1" Intensity="1.0">
              <ChildProcessors/>
            </Processor>
            <Processor Type="ModulatorChain" ID="P6 Modulation" Bypassed="1" Intensity="1.0">
              <ChildProcessors/>
            </Processor>
            <Processor Type="ModulatorChain" ID="P7 Modulation" Bypassed="1" Intensity="1.0">
              <ChildProcessors/>
            </Processor>
            <Processor Type="ModulatorChain" ID="P8 Modulation" Bypassed="1" Intensity="1.0">
              <ChildProcessors/>
            </Processor>
          </ChildProcessors>
          <RoutingMatrix NumSourceChannels="2" Channel0="0" Send0="-1" Channel1="1" Send1="-1"/>
        </Processor>
        <Processor Type="SimpleGain" ID="Volume" Bypassed="0" Gain="0.0" Delay="0.0"
                   Width="100.0" Balance="0.0" InvertPolarity="0.0">
          <ChildProcessors>
            <Processor Type="ModulatorChain" ID="Gain Modulation" Bypassed="0" Intensity="1.0">
              <ChildProcessors/>
            </Processor>
            <Processor Type="ModulatorChain" ID="Delay Modulation" Bypassed="0" Intensity="1.0">
              <ChildProcessors/>
            </Processor>
            <Processor Type="ModulatorChain" ID="Width Modulation" Bypassed="0" Intensity="1.0">
              <ChildProcessors/>
            </Processor>
            <Processor Type="ModulatorChain" ID="Pan Modulation" Bypassed="0" Intensity="1.0">
              <ChildProcessors/>
            </Processor>
          </ChildProcessors>
          <RoutingMatrix NumSourceChannels="2" Channel0="0" Send0="-1" Channel1="1" Send1="-1"/>
        </Processor>
      </ChildProcessors>
    </Processor>
    <Processor Type="AudioLooper" ID="Audio Loop Player1" Bypassed="0" Gain="1.0"
               Balance="0.0" VoiceLimit="256.0" KillFadeTime="20.0" IconColour="0"
               SyncMode="1.0" PitchTracking="0.0" LoopEnabled="1.0" RootNote="64.0"
               SampleStartMod="0.0" Reversed="0.0" FileName="{PROJECT_FOLDER}Athmosphere/Granite Spitting.flac"
               min="0" max="532763" loopStart="0" loopEnd="532763">
      <ChildProcessors>
        <Processor Type="MidiProcessorChain" ID="Midi Processor" Bypassed="0">
          <ChildProcessors/>
        </Processor>
        <Processor Type="ModulatorChain" ID="GainModulation" Bypassed="0" Intensity="1.0">
          <ChildProcessors>
            <Processor Type="SimpleEnvelope" ID="DefaultEnvelope1" Bypassed="0" Monophonic="0.0"
                       Retrigger="1.0" Intensity="1.0" Attack="10.0" Release="500.0"
                       LinearMode="1.0">
              <ChildProcessors>
                <Processor Type="ModulatorChain" ID="Attack Time Modulation" Bypassed="0"
                           Intensity="1.0">
                  <ChildProcessors/>
                </Processor>
              </ChildProcessors>
            </Processor>
          </ChildProcessors>
        </Processor>
        <Processor Type="ModulatorChain" ID="PitchModulation" Bypassed="0" Intensity="0.0">
          <ChildProcessors/>
        </Processor>
        <Processor Type="EffectChain" ID="FX" Bypassed="0">
          <ChildProcessors>
            <Processor Type="SimpleGain" ID="Gain1" Bypassed="0" Gain="0.0" Delay="0.0"
                       Width="100.0" Balance="0.0" InvertPolarity="0.0">
              <ChildProcessors>
                <Processor Type="ModulatorChain" ID="Gain Modulation" Bypassed="0" Intensity="1.0">
                  <ChildProcessors/>
                </Processor>
                <Processor Type="ModulatorChain" ID="Delay Modulation" Bypassed="0" Intensity="1.0">
                  <ChildProcessors/>
                </Processor>
                <Processor Type="ModulatorChain" ID="Width Modulation" Bypassed="0" Intensity="1.0">
                  <ChildProcessors/>
                </Processor>
                <Processor Type="ModulatorChain" ID="Pan Modulation" Bypassed="0" Intensity="1.0">
                  <ChildProcessors/>
                </Processor>
              </ChildProcessors>
              <RoutingMatrix NumSourceChannels="2" Channel0="0" Send0="-1" Channel1="1" Send1="-1"/>
            </Processor>
          </ChildProcessors>
        </Processor>
      </ChildProcessors>
      <RoutingMatrix NumSourceChannels="2" Channel0="0" Send0="-1" Channel1="1" Send1="-1"/>
    </Processor>
    <Processor Type="AudioLooper" ID="Audio Loop Player2" Bypassed="0" Gain="1.0"
               Balance="0.0" VoiceLimit="256.0" KillFadeTime="20.0" IconColour="0"
               SyncMode="1.0" PitchTracking="0.0" LoopEnabled="1.0" RootNote="34.0"
               SampleStartMod="0.0" Reversed="0.0" FileName="{PROJECT_FOLDER}Drones/Dew.flac"
               min="0" max="938967" loopStart="0" loopEnd="938967">
      <ChildProcessors>
        <Processor Type="MidiProcessorChain" ID="Midi Processor" Bypassed="0">
          <ChildProcessors/>
        </Processor>
        <Processor Type="ModulatorChain" ID="GainModulation" Bypassed="0" Intensity="1.0">
          <ChildProcessors>
            <Processor Type="SimpleEnvelope" ID="DefaultEnvelope2" Bypassed="0" Monophonic="0.0"
                       Retrigger="1.0" Intensity="1.0" Attack="10.0" Release="10.0"
                       LinearMode="1.0">
              <ChildProcessors>
                <Processor Type="ModulatorChain" ID="Attack Time Modulation" Bypassed="0"
                           Intensity="1.0">
                  <ChildProcessors/>
                </Processor>
              </ChildProcessors>
            </Processor>
          </ChildProcessors>
        </Processor>
        <Processor Type="ModulatorChain" ID="PitchModulation" Bypassed="0" Intensity="0.0">
          <ChildProcessors/>
        </Processor>
        <Processor Type="EffectChain" ID="FX" Bypassed="0">
          <ChildProcessors>
            <Processor Type="SimpleGain" ID="Gain2" Bypassed="0" Gain="-100.0" Delay="0.0"
                       Width="100.0" Balance="0.0" InvertPolarity="0.0">
              <ChildProcessors>
                <Processor Type="ModulatorChain" ID="Gain Modulation" Bypassed="0" Intensity="1.0">
                  <ChildProcessors/>
                </Processor>
                <Processor Type="ModulatorChain" ID="Delay Modulation" Bypassed="0" Intensity="1.0">
                  <ChildProcessors/>
                </Processor>
                <Processor Type="ModulatorChain" ID="Width Modulation" Bypassed="0" Intensity="1.0">
                  <ChildProcessors/>
                </Processor>
                <Processor Type="ModulatorChain" ID="Pan Modulation" Bypassed="0" Intensity="1.0">
                  <ChildProcessors/>
                </Processor>
              </ChildProcessors>
              <RoutingMatrix NumSourceChannels="2" Channel0="0" Send0="-1" Channel1="1" Send1="-1"/>
            </Processor>
          </ChildProcessors>
        </Processor>
      </ChildProcessors>
      <RoutingMatrix NumSourceChannels="2" Channel0="0" Send0="-1" Channel1="1" Send1="-1"/>
    </Processor>
  </ChildProcessors>
  <RoutingMatrix NumSourceChannels="2" Channel0="0" Send0="-1" Channel1="1" Send1="-1"/>
  <macro_controls>
    <macro name="Macro 1" value="0.0" midi_cc="-1"/>
    <macro name="Macro 2" value="0.0" midi_cc="-1"/>
    <macro name="Macro 3" value="0.0" midi_cc="-1"/>
    <macro name="Macro 4" value="0.0" midi_cc="-1"/>
    <macro name="Macro 5" value="0.0" midi_cc="-1"/>
    <macro name="Macro 6" value="0.0" midi_cc="-1"/>
    <macro name="Macro 7" value="0.0" midi_cc="-1"/>
    <macro name="Macro 8" value="0.0" midi_cc="-1"/>
  </macro_controls>
  <MidiAutomation/>
  <MPEData Enabled="0"/>
</Processor>
